resistics/__init__.py
resistics/resisticsConfig.ini
resistics/calibrate/__init__.py
resistics/calibrate/calibrator.py
resistics/calibrate/data.py
resistics/calibrate/io.py
resistics/calibrate/utils.py
resistics/common/__init__.py
resistics/common/base.py
resistics/common/checks.py
resistics/common/io.py
resistics/common/math.py
resistics/common/plot.py
resistics/common/print.py
resistics/common/smooth.py
resistics/config/__init__.py
resistics/config/data.py
resistics/config/defaults.py
resistics/config/io.py
resistics/decimate/__init__.py
resistics/decimate/decimator.py
resistics/decimate/evalfreqs.py
resistics/decimate/parameters.py
resistics/mask/__init__.py
resistics/mask/calculator.py
resistics/mask/data.py
resistics/mask/io.py
resistics/project/__init__.py
resistics/project/data.py
resistics/project/io.py
resistics/project/mask.py
resistics/project/preprocess.py
resistics/project/shortcuts.py
resistics/project/spectra.py
resistics/project/statistics.py
resistics/project/time.py
resistics/project/transfunc.py
resistics/project/utils.py
resistics/regression/__init__.py
resistics/regression/compute.py
resistics/regression/local.py
resistics/regression/remote.py
resistics/regression/robust.py
resistics/site/__init__.py
resistics/site/data.py
resistics/spectra/__init__.py
resistics/spectra/calculator.py
resistics/spectra/data.py
resistics/spectra/io.py
resistics/statistics/__init__.py
resistics/statistics/calculator.py
resistics/statistics/data.py
resistics/statistics/io.py
resistics/statistics/utils.py
resistics/time/__init__.py
resistics/time/clean.py
resistics/time/data.py
resistics/time/filter.py
resistics/time/interp.py
resistics/time/math.py
resistics/time/reader.py
resistics/time/reader_ascii.py
resistics/time/reader_ats.py
resistics/time/reader_internal.py
resistics/time/reader_lemib423.py
resistics/time/reader_lemib423e.py
resistics/time/reader_phoenix.py
resistics/time/reader_spam.py
resistics/time/utils.py
resistics/time/writer.py
resistics-0.0.6.dist-info/LICENCE.txt
resistics-0.0.6.dist-info/METADATA
resistics-0.0.6.dist-info/WHEEL
resistics-0.0.6.dist-info/top_level.txt
resistics-0.0.6.dist-info/RECORD
