Metadata-Version: 2.1
Name: resistics
Version: 0.0.6
Summary: Robust magnetotelluric processing package
Home-page: https://www.resistics.io
Author: Neeraj Shah
Author-email: resistics@outlook.com
License: MIT
Project-URL: Source, https://github.com/resistics/resistics
Project-URL: Tracker, https://github.com/resistics/resistics/issues
Keywords: geophysics magnetotellurics electromagnetic resistivity statistics
Platform: UNKNOWN
Classifier: Development Status :: 4 - Beta
Classifier: Programming Language :: Python :: 3
Classifier: Operating System :: OS Independent
Classifier: License :: OSI Approved :: MIT License
Classifier: Intended Audience :: Science/Research
Requires-Python: >=3.6
Requires-Dist: numpy
Requires-Dist: scipy
Requires-Dist: pyfftw
Requires-Dist: matplotlib
Requires-Dist: configobj
